aalam_common/__init__.py
aalam_common/auth.py
aalam_common/config.py
aalam_common/config_helper.py
aalam_common/debug.py
aalam_common/error-unauthorized.html
aalam_common/exceptions.py
aalam_common/hooks.py
aalam_common/main.py
aalam_common/redisdb.py
aalam_common/role_mgmt.py
aalam_common/sqa.py
aalam_common/system.py
aalam_common/utils.py
aalam_common/wsgi.py
aalam_common-0.1.78.dist-info/LICENSE
aalam_common-0.1.78.dist-info/METADATA
aalam_common-0.1.78.dist-info/WHEEL
aalam_common-0.1.78.dist-info/entry_points.txt
aalam_common-0.1.78.dist-info/top_level.txt
aalam_common-0.1.78.dist-info/RECORD
